json2video/__init__.py
json2video/client.py
json2video-2.0.0.dist-info/METADATA
json2video-2.0.0.dist-info/WHEEL
json2video-2.0.0.dist-info/top_level.txt
json2video-2.0.0.dist-info/RECORD
